Metadata-Version: 1.0
Name: WtSubspace
Version: 0.2
Summary: Weighted random subspace method for classification
Home-page: https://github.com/PWuJuveOKC/WtSubspace
Author: Peng Wu
Author-email: pwusff@gmail.com
License: LICENSE.txt
Keywords: Random Subspace,Weighted Method,Classification
Platform: UNKNOWN
